{
  "table": "Settings",
  "key": "FetchImages.Always",
  "value": {
    "extractionState": "manual",
    "localizations": {
      "de": { "stringUnit": { "state": "translated", "value": "Immer" } },
      "en": { "stringUnit": { "state": "translated", "value": "Always" } },
      "fr": { "stringUnit": { "state": "translated", "value": "Toujours" } },
      "it": { "stringUnit": { "state": "translated", "value": "Sempre" } },
      "ja": { "stringUnit": { "state": "translated", "value": "常に" } },
      "ko": { "stringUnit": { "state": "translated", "value": "항상" } },
      "vi": { "stringUnit": { "state": "translated", "value": "Luôn luôn" } },
      "zh-Hans": { "stringUnit": { "state": "translated", "value": "始终" } },
      "zh-Hant": { "stringUnit": { "state": "translated", "value": "一律" } }
    }
  }
}
