{
  "table": "Settings",
  "key": "FetchImages",
  "value": {
    "extractionState": "manual",
    "localizations": {
      "de": { "stringUnit": { "state": "translated", "value": "Bilder abrufen" } },
      "en": { "stringUnit": { "state": "translated", "value": "Fetch Images" } },
      "fr": { "stringUnit": { "state": "translated", "value": "Récupérer les images" } },
      "it": { "stringUnit": { "state": "translated", "value": "Scarica immagini" } },
      "ja": { "stringUnit": { "state": "translated", "value": "画像を取得" } },
      "ko": { "stringUnit": { "state": "translated", "value": "이미지 가져오기" } },
      "vi": { "stringUnit": { "state": "translated", "value": "Tải hình ảnh" } },
      "zh-Hans": { "stringUnit": { "state": "translated", "value": "获取图片" } },
      "zh-Hant": { "stringUnit": { "state": "translated", "value": "擷取圖片" } }
    }
  }
}
